{
  "artist_num": 914,
  "artist_id": "K8vZ917hkhV",
  "events": [
    {
      "title": "Little Stranger",
      "start_date": "2024-10-19",
      "end_date": "2024-10-19",
      "image_url": "https://s1.ticketm.net/dam/a/c0c/d3a920b9-40ef-4408-a9f3-8271d1542c0c_TABLET_LANDSCAPE_3_2.jpg",
      "location": "Washington, District of Columbia, United States Of America",
      "description": "No description available",
      "ticket_link": "https://www.ticketmaster.com/little-stranger-washington-district-of-columbia-10-19-2024/event/1500609A972E2B22"
    },
    {
      "title": "Little Stranger",
      "start_date": "2024-10-18",
      "end_date": "2024-10-18",
      "image_url": "https://s1.ticketm.net/dam/a/c0c/d3a920b9-40ef-4408-a9f3-8271d1542c0c_TABLET_LANDSCAPE_3_2.jpg",
      "location": "Charlotte, North Carolina, United States Of America",
      "description": "The Fillmore Is A General Admission Standing Room Only Venue Unless Otherwise Noted. All Ages Welcome Doors: 7:00PM Show: 8:00PM Ticket prices will increase the day of the show. All dates, acts, and ticket prices subject to change without notice. All tickets are subject to applicable service fees via all points of purchase.",
      "ticket_link": "https://concerts.livenation.com/little-stranger-charlotte-north-carolina-10-18-2024/event/2D00609DAF63420C"
    },
    {
      "title": "Little Stranger",
      "start_date": "2024-10-10",
      "end_date": "2024-10-10",
      "image_url": "https://s1.ticketm.net/dam/a/c0c/d3a920b9-40ef-4408-a9f3-8271d1542c0c_TABLET_LANDSCAPE_3_2.jpg",
      "location": "Brooklyn, New York, United States Of America",
      "description": "No description available",
      "ticket_link": "https://concerts.livenation.com/little-stranger-brooklyn-new-york-10-10-2024/event/0000609AFCBA8C70"
    },
    {
      "title": "Little Stranger",
      "start_date": "2024-10-03",
      "end_date": "2024-10-03",
      "image_url": "https://s1.ticketm.net/dam/a/c0c/d3a920b9-40ef-4408-a9f3-8271d1542c0c_TABLET_LANDSCAPE_3_2.jpg",
      "location": "Chicago, Illinois, United States Of America",
      "description": "Doors open at 7PM. Performance begins at 8PM. This show is for AGES 17 AND OLDER. Valid Photo ID is required for age restricted shows. Forms of valid ID are current and non-expired Driver's License, State ID, or Passport. House of Blues Chicago is a standing room only venue, all tickets are General Admission unless otherwise stated. *All support acts are subject to change without notice.*",
      "ticket_link": "https://concerts.livenation.com/little-stranger-chicago-illinois-10-03-2024/event/040060F6857B0A87"
    },
    {
      "title": "Little Stranger",
      "start_date": "2024-09-27",
      "end_date": "2024-09-27",
      "image_url": "https://s1.ticketm.net/dam/a/c0c/d3a920b9-40ef-4408-a9f3-8271d1542c0c_TABLET_LANDSCAPE_3_2.jpg",
      "location": "Kansas City, Missouri, United States Of America",
      "description": "Little Stranger with Wax, Jarv and Damn Skippy. General admission floor with reserved cabaret and high top table seating. There will be a $2 minor fee at the door for patrons under 21 years of age. Doors 7pm / Show 8pm",
      "ticket_link": "https://www.ticketmaster.com/little-stranger-kansas-city-missouri-09-27-2024/event/060060A9B2CC3B58"
    }
  ]
}