{
  "artist_num": 950,
  "artist_id": "K8vZ917qklV",
  "events": [
    {
      "title": "Night Tempo",
      "start_date": "2024-09-08",
      "end_date": "2024-09-08",
      "image_url": "https://s1.ticketm.net/dam/a/787/358f48b7-91f3-40a1-abc5-29e128a82787_TABLET_LANDSCAPE_16_9.jpg",
      "location": "Seattle, Washington, United States Of America",
      "description": "The Neptune Theatre is located in Seattle, Washington at 1313 NE 45th Street in Seattle's University District. This is a general admission event. The ADA section on the seating map does not represent a specific seat location. There is an 8 ticket limit for this event. Accounts found in violation of the posted ticket limit may be cancelled without notice. All sales are final. No refunds or exchanges. Unless otherwise noted, each person must have a ticket regardless of age. No babies in arms. Mobile ticket delivery will be delayed until 4 days prior to event.",
      "ticket_link": "https://www.ticketmaster.com/night-tempo-seattle-washington-09-08-2024/event/0F0060D2FB834E08"
    }
  ]
}