{
  "artist_num": 867,
  "artist_id": "K8vZ917Q5rf",
  "events": [
    {
      "title": "An Epic Night of Hits!",
      "start_date": "2024-11-09",
      "end_date": "2024-11-09",
      "image_url": "https://s1.ticketm.net/dam/a/79c/ac0737f1-36af-4adb-bc5a-88ac34b6179c_TABLET_LANDSCAPE_16_9.jpg",
      "location": "Tallahassee, Florida, United States Of America",
      "description": "Artist Lineup Includes, Jeezy and Muni Long",
      "ticket_link": "https://www.ticketmaster.com/an-epic-night-of-hits-tallahassee-florida-11-09-2024/event/22006114C59E299F"
    }
  ]
}