{
  "artist_num": 937,
  "artist_id": "K8vZ917ouCV",
  "events": [
    {
      "title": "COMPLETE | NOTHING TO SHOW TOUR 2024",
      "start_date": "2024-08-31",
      "end_date": "2024-08-31",
      "image_url": "https://s1.ticketm.net/dam/c/80b/f3cd8d24-c3ae-4fa0-b4bc-1ba99f9b380b_106091_TABLET_LANDSCAPE_16_9.jpg",
      "location": "Auckland, New Zealand, New Zealand",
      "description": "No description available",
      "ticket_link": "https://www.moshtix.co.nz/v2/event/complete-nothing-to-show-tour-2024/166787"
    }
  ]
}