{
  "artist_num": 3090,
  "artist_id": "K8vZ917QhyV",
  "events": [
    {
      "title": "Sammy Johnson",
      "start_date": "2024-09-21",
      "end_date": "2024-09-21",
      "image_url": "https://s1.ticketm.net/dam/a/42b/2aca7052-63f3-4937-81dc-6b57bff7142b_522641_TABLET_LANDSCAPE_3_2.jpg",
      "location": "San Diego, California, United States Of America",
      "description": "All Ages Welcome Doors: 6:00PM Show: 7:00PM *All times and supporting acts are subject to change* Tickets purchased from third-party outlets cannot be verified by our box office. If you have any issues with a third-party purchase, you must contact the third-party outlet directly. This event is open to all ages. All guests under the age of 18 must be accompanied by a parent, guardian, or responsible adult over the age of 25 with written authorization. Parking is available at the parking structure directly across the street from us on 29th St. Your ticket fee includes validation for the parking structure.",
      "ticket_link": "https://concerts.livenation.com/sammy-johnson-san-diego-california-09-21-2024/event/0B006106F8CA1D8E"
    }
  ]
}