{
  "artist_num": 1967,
  "artist_id": "K8vZ917QQOf",
  "events": [
    {
      "title": "Leanna Firestone",
      "start_date": "2024-11-16",
      "end_date": "2024-11-16",
      "image_url": "https://s1.ticketm.net/dam/a/2da/692c358d-d566-475d-a334-043b1b5222da_TABLET_LANDSCAPE_3_2.jpg",
      "location": "Houston, Texas, United States Of America",
      "description": "This is an all ages standing room only event. Doors open at 7:30PM",
      "ticket_link": "https://concerts.livenation.com/leanna-firestone-houston-texas-11-16-2024/event/3A0060C6CD984CDA"
    },
    {
      "title": "LEANNA FIRESTONE",
      "start_date": "2024-11-14",
      "end_date": "2024-11-14",
      "image_url": "https://s1.ticketm.net/dam/a/2da/692c358d-d566-475d-a334-043b1b5222da_TABLET_LANDSCAPE_3_2.jpg",
      "location": "Phoenix, Arizona, United States Of America",
      "description": "Psyko Steve PresentsLEANNA FIRESTONEwith special guestSUNDIALThursday, November 14th 2024Doors at 7:30 / Show at 8:3016+Advance General Admission Ticket: $25 + feesDay of Show GA Ticket: $30 + feesVIP$75 + feesIncludes-one (1) general admission ticket-early venue /merch shopping access-3 month code to join Leannas $5 Patreon tier-acoustic soundcheck experience-exclusive Q and A session with Leanna-photo with leanna-exclusive laminate",
      "ticket_link": "https://www.ticketweb.com/event/leanna-firestone-crescent-ballroom-tickets/13669133"
    },
    {
      "title": "Leanna Firestone",
      "start_date": "2024-11-13",
      "end_date": "2024-11-13",
      "image_url": "https://s1.ticketm.net/dam/a/2da/692c358d-d566-475d-a334-043b1b5222da_TABLET_LANDSCAPE_3_2.jpg",
      "location": "Anaheim, California, United States Of America",
      "description": "General Admission Standing Only. Age Restriction: This is an all-ages event. All guests, regardless of age, are required to have a ticket for entry. Doors: 7:30pm Support: sundial All acts subject to change.",
      "ticket_link": "https://concerts.livenation.com/leanna-firestone-anaheim-california-11-13-2024/event/090060C6FA605C6B"
    },
    {
      "title": "Leanna Firestone",
      "start_date": "2024-11-01",
      "end_date": "2024-11-01",
      "image_url": "https://s1.ticketm.net/dam/a/2da/692c358d-d566-475d-a334-043b1b5222da_TABLET_LANDSCAPE_3_2.jpg",
      "location": "Denver, Colorado, United States Of America",
      "description": "Doors: 7:30PM Show: 8:30PM This show is ALL AGES All acts subject to change without notice",
      "ticket_link": "https://concerts.livenation.com/leanna-firestone-denver-colorado-11-01-2024/event/1E0060C7B66D61D4"
    },
    {
      "title": "Leanna Firestone",
      "start_date": "2024-09-08",
      "end_date": "2024-09-08",
      "image_url": "https://s1.ticketm.net/dam/a/2da/692c358d-d566-475d-a334-043b1b5222da_TABLET_LANDSCAPE_3_2.jpg",
      "location": "Manchester, Unknown State, Great Britain",
      "description": "No description available",
      "ticket_link": "https://www.ticketweb.uk/event/leanna-firestone-the-deaf-institute-tickets/13670853?REFERRAL_ID=tmfeed"
    },
    {
      "title": "Leanna Firestone",
      "start_date": "2024-09-07",
      "end_date": "2024-09-07",
      "image_url": "https://s1.ticketm.net/dam/a/2da/692c358d-d566-475d-a334-043b1b5222da_TABLET_LANDSCAPE_3_2.jpg",
      "location": "London, Unknown State, Great Britain",
      "description": "No description available",
      "ticket_link": "https://www.ticketweb.uk/event/leanna-firestone-the-camden-assembly-tickets/13670753?REFERRAL_ID=tmfeed"
    },
    {
      "title": "Leanna Firestone",
      "start_date": "2024-09-06",
      "end_date": "2024-09-06",
      "image_url": "https://s1.ticketm.net/dam/a/2da/692c358d-d566-475d-a334-043b1b5222da_TABLET_LANDSCAPE_3_2.jpg",
      "location": "Bristol, Unknown State, Great Britain",
      "description": "No description available",
      "ticket_link": "https://www.ticketweb.uk/event/leanna-firestone-thekla-tickets/13670733?REFERRAL_ID=tmfeed"
    },
    {
      "title": "Leanna Firestone",
      "start_date": "2024-09-04",
      "end_date": "2024-09-04",
      "image_url": "https://s1.ticketm.net/dam/a/2da/692c358d-d566-475d-a334-043b1b5222da_TABLET_LANDSCAPE_3_2.jpg",
      "location": "Glasgow, Unknown State, Great Britain",
      "description": "No description available",
      "ticket_link": "https://www.ticketmaster.co.uk/leanna-firestone-glasgow-04-09-2024/event/360060BC9F18313A"
    }
  ]
}